[
  {
    "firstName": "Stephen",
    "lastName": "Hamilton",
    "email": "viumamun@li.pg",
    "password": "sNbkQ9MMJ35d23q",
    "phone": "123456789",
    "roles": "user",
    "membership_status": "",
    "country": "St. Lucia",
    "address": "Dirección 1",
    "city": "Ciudad 1"
  },
  {
    "firstName": "Cecelia",
    "lastName": "Reid",
    "email": "miw@fodzunza.gb",
    "password": "Jl73s",
    "phone": "234567890",
    "roles": "user",
    "membership_status": "",
    "country": "Djibouti",
    "address": "Dirección 2",
    "city": "Ciudad 2"
  },
  {
    "firstName": "Randy",
    "lastName": "Miller",
    "email": "ez@cu.is",
    "password": "MEJm0o857TYChDXu8",
    "phone": "234567890",
    "roles": "user",
    "membership_status": "",
    "country": "Guatemala",
    "address": "Dirección 2",
    "city": "Ciudad 2"
  },
  {
    "firstName": "Allie",
    "lastName": "Price",
    "email": "hegapi@ijibifof.mr",
    "password": "SUJpG2zBJG0PEW7JPKV7",
    "phone": "345678901",
    "roles": "user",
    "membership_status": "",
    "country": "New Zealand",
    "address": "Dirección 3",
    "city": "Ciudad 3"
  },
  {
    "firstName": "Alice",
    "lastName": "Wagner",
    "email": "ana@lieraec.tw",
    "password": "p1n1ac91",
    "phone": "456789012",
    "roles": "user",
    "membership_status": "",
    "country": "Morocco",
    "address": "Dirección 4",
    "city": "Ciudad 4"
  },
  {
    "firstName": "Mina",
    "lastName": "McGee",
    "email": "gorpa@goh.uy",
    "password": "8ptjlxe9dT",
    "phone": "567890123",
    "roles": "user",
    "membership_status": "",
    "country": "Bahamas",
    "address": "Dirección 5",
    "city": "Ciudad 5"
  },
  {
    "firstName": "Johnny",
    "lastName": "Rodgers",
    "email": "tomnicaf@ku.cf",
    "password": "OEKJAFHQpisu10",
    "phone": "678901234",
    "roles": "user",
    "membership_status": "",
    "country": "Mozambique",
    "address": "Dirección 6",
    "city": "Ciudad 6"
  },
  {
    "firstName": "Barbara",
    "lastName": "Parker",
    "email": "peetuli@cak.tk",
    "password": "AMmnjeV8DO6",
    "phone": "789012345",
    "roles": "user",
    "membership_status": "",
    "country": "Suriname",
    "address": "Dirección 7",
    "city": "Ciudad 7"
  },
  {
    "firstName": "Millie",
    "lastName": "Moore",
    "email": "tik@owometciv.gl",
    "password": "FXFjvH",
    "phone": "890123456",
    "roles": "user",
    "membership_status": "",
    "country": "Panama",
    "address": "Dirección 8",
    "city": "Ciudad 8"
  },
  {
    "firstName": "David",
    "lastName": "Miles",
    "email": "vabhefat@karaloj.gw",
    "password": "duBZ2105dIC8dNQgS",
    "phone": "901234567",
    "roles": "user",
    "membership_status": "",
    "country": "Timor-Leste",
    "address": "Dirección 9",
    "city": "Ciudad 9"
  },
  {
    "firstName": "Adele",
    "lastName": "Franklin",
    "email": "le@tevluwo.bt",
    "password": "Twrl1",
    "phone": "1234567890",
    "roles": "user",
    "membership_status": "",
    "country": "Czech Republic",
    "address": "Dirección 10",
    "city": "Ciudad 10"
  }
]
